bigwig_io.cpython-313-darwin.so
bigwig_io/binding.cpp
bigwig_io/data_tree.cpp
bigwig_io/data_values.cpp
bigwig_io/genomes.cpp
bigwig_io/headers.cpp
bigwig_io/locs.cpp
bigwig_io/main.cpp
bigwig_io/reader.cpp
bigwig_io/util/byte_util.cpp
bigwig_io/util/file_util.cpp
bigwig_io/util/generator_util.cpp
bigwig_io/util/main.cpp
bigwig_io/util/map_util.cpp
bigwig_io/util/parallel_util.cpp
bigwig_io/util/progress_util.cpp
bigwig_io/util/string_util.cpp
bigwig_io/util/tree_util.cpp
bigwig_io-0.1.11.data/data/bigwig_io/binding.cpp
bigwig_io-0.1.11.data/data/bigwig_io/byte_util.cpp
bigwig_io-0.1.11.data/data/bigwig_io/data_tree.cpp
bigwig_io-0.1.11.data/data/bigwig_io/data_values.cpp
bigwig_io-0.1.11.data/data/bigwig_io/file_util.cpp
bigwig_io-0.1.11.data/data/bigwig_io/generator_util.cpp
bigwig_io-0.1.11.data/data/bigwig_io/genomes.cpp
bigwig_io-0.1.11.data/data/bigwig_io/headers.cpp
bigwig_io-0.1.11.data/data/bigwig_io/locs.cpp
bigwig_io-0.1.11.data/data/bigwig_io/main.cpp
bigwig_io-0.1.11.data/data/bigwig_io/map_util.cpp
bigwig_io-0.1.11.data/data/bigwig_io/parallel_util.cpp
bigwig_io-0.1.11.data/data/bigwig_io/progress_util.cpp
bigwig_io-0.1.11.data/data/bigwig_io/reader.cpp
bigwig_io-0.1.11.data/data/bigwig_io/string_util.cpp
bigwig_io-0.1.11.data/data/bigwig_io/tree_util.cpp
bigwig_io-0.1.11.dist-info/licenses/LICENSE
bigwig_io-0.1.11.dist-info/METADATA
bigwig_io-0.1.11.dist-info/WHEEL
bigwig_io-0.1.11.dist-info/top_level.txt
bigwig_io-0.1.11.dist-info/RECORD
