Metadata-Version: 2.4
Name: bigwig_io
Version: 0.1.11
Summary: Process bigWig and bigBed files
Author-email: Arthur Gouhier <ajgouhier@gmail.com>
License-Expression: MIT
Project-URL: Repository, https://github.com/ajgouhier/bigwig_io
Requires-Python: >=3.8
License-File: LICENSE
Requires-Dist: numpy
Requires-Dist: pybind11>=2.6.0
Dynamic: license-file
